{
 "cf225356578326308b16a0fd03ff3fa72fe3da07": {
  "num_adds_if": 0,
  "num_dels_if": 0,
  "num_mod_total_if": 0,
  "num_adds_loop": 0,
  "num_dels_loop": 0,
  "num_mod_total_loop": 0,
  "file_hash": "cf225356578326308b16a0fd03ff3fa72fe3da07",
  "num_adds": 1,
  "num_dels": 1,
  "num_mod_lns_total": 2,
  "mod_files_lst": [
   "include/net/llc_pdu.h"
  ],
  "entropy": 0.0
 },
 "451677c46feb5fb39cb7f71035b8716064fcbd57": {
  "num_adds_if": 1,
  "num_dels_if": 1,
  "num_mod_total_if": 2,
  "num_adds_loop": 0,
  "num_dels_loop": 0,
  "num_mod_total_loop": 0,
  "file_hash": "451677c46feb5fb39cb7f71035b8716064fcbd57",
  "num_adds": 4,
  "num_dels": 1,
  "num_mod_lns_total": 5,
  "mod_files_lst": [
   "net/llc/af_llc.c"
  ],
  "entropy": 0.0
 },
 "59c6196e59a4b85d9c994e70ff20a460cdbaa003": {
  "num_adds_if": 4,
  "num_dels_if": 4,
  "num_mod_total_if": 8,
  "num_adds_loop": 0,
  "num_dels_loop": 0,
  "num_mod_total_loop": 0,
  "file_hash": "59c6196e59a4b85d9c994e70ff20a460cdbaa003",
  "num_adds": 11,
  "num_dels": 9,
  "num_mod_lns_total": 20,
  "mod_files_lst": [
   "net/llc/llc_c_ac.c"
  ],
  "entropy": 0.0
 },
 "cb422c464bdaeeb3b9ad4539010e357bf1bd1745": {
  "num_adds_if": 0,
  "num_dels_if": 0,
  "num_mod_total_if": 0,
  "num_adds_loop": 0,
  "num_dels_loop": 0,
  "num_mod_total_loop": 0,
  "file_hash": "cb422c464bdaeeb3b9ad4539010e357bf1bd1745",
  "num_adds": 1,
  "num_dels": 1,
  "num_mod_lns_total": 2,
  "mod_files_lst": [
   "net/ipv6/ipv6_sockglue.c"
  ],
  "entropy": 0.0
 },
 "12da2a435c1e8b9abb780d928ccbf04fc3d860a7": {
  "num_adds_if": 1,
  "num_dels_if": 1,
  "num_mod_total_if": 2,
  "num_adds_loop": 0,
  "num_dels_loop": 0,
  "num_mod_total_loop": 0,
  "file_hash": "12da2a435c1e8b9abb780d928ccbf04fc3d860a7",
  "num_adds": 3,
  "num_dels": 2,
  "num_mod_lns_total": 5,
  "mod_files_lst": [
   "net/ipv6/addrconf.c"
  ],
  "entropy": 0.0
 },
 "4060994c3e337b40e0f6fa8ce2cc178e021baf3d": {
  "num_adds_if": 101,
  "num_dels_if": 54,
  "num_mod_total_if": 155,
  "num_adds_loop": 22,
  "num_dels_loop": 16,
  "num_mod_total_loop": 38,
  "file_hash": "4060994c3e337b40e0f6fa8ce2cc178e021baf3d",
  "num_adds": 1481,
  "num_dels": 1097,
  "num_mod_lns_total": 2578,
  "mod_files_lst": [
   "Documentation/x86_64/boot-options.txt",
   "Documentation/x86_64/mm.txt",
   "arch/i386/kernel/acpi/boot.c",
   "arch/i386/kernel/cpu/amd.c",
   "arch/i386/kernel/cpu/common.c",
   "arch/i386/kernel/cpu/intel.c",
   "arch/i386/kernel/cpu/intel_cacheinfo.c",
   "arch/i386/kernel/cpu/mtrr/main.c",
   "arch/i386/kernel/cpu/proc.c",
   "arch/i386/kernel/smpboot.c",
   "arch/i386/kernel/srat.c",
   "arch/ia64/Kconfig",
   "arch/x86_64/Kconfig",
   "arch/x86_64/Kconfig.debug",
   "arch/x86_64/defconfig",
   "arch/x86_64/ia32/ia32_aout.c",
   "arch/x86_64/ia32/ia32_binfmt.c",
   "arch/x86_64/kernel/Makefile",
   "arch/x86_64/kernel/aperture.c",
   "arch/x86_64/kernel/apic.c",
   "arch/x86_64/kernel/e820.c",
   "arch/x86_64/kernel/entry.S",
   "arch/x86_64/kernel/head.S",
   "arch/x86_64/kernel/head64.c",
   "arch/x86_64/kernel/i8259.c",
   "arch/x86_64/kernel/io_apic.c",
   "arch/x86_64/kernel/mce.c",
   "arch/x86_64/kernel/mce_amd.c",
   "arch/x86_64/kernel/mpparse.c",
   "arch/x86_64/kernel/pci-gart.c",
   "arch/x86_64/kernel/process.c",
   "arch/x86_64/kernel/reboot.c",
   "arch/x86_64/kernel/setup.c",
   "arch/x86_64/kernel/setup64.c",
   "arch/x86_64/kernel/signal.c",
   "arch/x86_64/kernel/smp.c",
   "arch/x86_64/kernel/smpboot.c",
   "arch/x86_64/kernel/sys_x86_64.c",
   "arch/x86_64/kernel/traps.c",
   "arch/x86_64/kernel/vmlinux.lds.S",
   "arch/x86_64/kernel/x8664_ksyms.c",
   "arch/x86_64/lib/clear_page.S",
   "arch/x86_64/lib/copy_page.S",
   "arch/x86_64/lib/memcpy.S",
   "arch/x86_64/lib/memset.S",
   "arch/x86_64/mm/fault.c",
   "arch/x86_64/mm/init.c",
   "arch/x86_64/mm/k8topology.c",
   "arch/x86_64/mm/numa.c",
   "arch/x86_64/mm/srat.c",
   "drivers/char/agp/amd64-agp.c",
   "include/asm-generic/sections.h",
   "include/asm-i386/mach-default/mach_reboot.h",
   "include/asm-i386/processor.h",
   "include/asm-x86_64/apic.h",
   "include/asm-x86_64/cache.h",
   "include/asm-x86_64/desc.h",
   "include/asm-x86_64/dma.h",
   "include/asm-x86_64/hpet.h",
   "include/asm-x86_64/hw_irq.h",
   "include/asm-x86_64/ia32.h",
   "include/asm-x86_64/mce.h",
   "include/asm-x86_64/mmzone.h",
   "include/asm-x86_64/mpspec.h",
   "include/asm-x86_64/msr.h",
   "include/asm-x86_64/numa.h",
   "include/asm-x86_64/page.h",
   "include/asm-x86_64/pda.h",
   "include/asm-x86_64/pgtable.h",
   "include/asm-x86_64/processor.h",
   "include/asm-x86_64/proto.h",
   "include/asm-x86_64/rwsem.h",
   "include/asm-x86_64/smp.h",
   "include/asm-x86_64/spinlock.h",
   "include/asm-x86_64/topology.h",
   "include/asm-x86_64/unistd.h",
   "include/linux/bitops.h",
   "include/linux/gfp.h",
   "include/linux/mm.h",
   "include/linux/mmzone.h",
   "mm/filemap.c",
   "mm/page_alloc.c"
  ],
  "entropy": 4.754692780733516
 },
 "d3ee871e63d0a0c70413dc0aa5534b8d6cd6ec37": {
  "num_adds_if": 0,
  "num_dels_if": 0,
  "num_mod_total_if": 0,
  "num_adds_loop": 1,
  "num_dels_loop": 0,
  "num_mod_total_loop": 1,
  "file_hash": "d3ee871e63d0a0c70413dc0aa5534b8d6cd6ec37",
  "num_adds": 17,
  "num_dels": 4,
  "num_mod_lns_total": 21,
  "mod_files_lst": [
   "arch/x86_64/kernel/setup.c",
   "arch/x86_64/mm/numa.c"
  ],
  "entropy": 0.5916727785823275
 },
 "8893166ff8694f36655009aa9bf8e7f2e1c9339f": {
  "num_adds_if": 1,
  "num_dels_if": 1,
  "num_mod_total_if": 2,
  "num_adds_loop": 0,
  "num_dels_loop": 0,
  "num_mod_total_loop": 0,
  "file_hash": "8893166ff8694f36655009aa9bf8e7f2e1c9339f",
  "num_adds": 9,
  "num_dels": 6,
  "num_mod_lns_total": 15,
  "mod_files_lst": [
   "arch/x86_64/kernel/mpparse.c",
   "include/asm-x86_64/mpspec.h"
  ],
  "entropy": 0.8366407419411673
 },
 "9e43e1b7c7c9872da032442d8e4bb112a02d16f4": {
  "num_adds_if": 0,
  "num_dels_if": 4,
  "num_mod_total_if": 4,
  "num_adds_loop": 0,
  "num_dels_loop": 0,
  "num_mod_total_loop": 0,
  "file_hash": "9e43e1b7c7c9872da032442d8e4bb112a02d16f4",
  "num_adds": 10,
  "num_dels": 65,
  "num_mod_lns_total": 75,
  "mod_files_lst": [
   "Documentation/x86_64/boot-options.txt",
   "arch/x86_64/Kconfig.debug",
   "arch/x86_64/kernel/traps.c",
   "arch/x86_64/mm/fault.c",
   "arch/x86_64/mm/init.c"
  ],
  "entropy": 1.7638592362816554
 },
 "ffd10a2b77bca50dd05ba26acd5a6e68bcc8f61f": {
  "num_adds_if": 0,
  "num_dels_if": 3,
  "num_mod_total_if": 3,
  "num_adds_loop": 0,
  "num_dels_loop": 0,
  "num_mod_total_loop": 0,
  "file_hash": "ffd10a2b77bca50dd05ba26acd5a6e68bcc8f61f",
  "num_adds": 1,
  "num_dels": 6,
  "num_mod_lns_total": 7,
  "mod_files_lst": [
   "arch/x86_64/mm/k8topology.c",
   "arch/x86_64/mm/numa.c",
   "arch/x86_64/mm/srat.c"
  ],
  "entropy": 1.3787834934861753
 },
 "e583538f077d5f70191670b47a046ba436ec3428": {
  "num_adds_if": 1,
  "num_dels_if": 1,
  "num_mod_total_if": 2,
  "num_adds_loop": 0,
  "num_dels_loop": 0,
  "num_mod_total_loop": 0,
  "file_hash": "e583538f077d5f70191670b47a046ba436ec3428",
  "num_adds": 13,
  "num_dels": 7,
  "num_mod_lns_total": 20,
  "mod_files_lst": [
   "Documentation/x86_64/boot-options.txt",
   "arch/x86_64/kernel/mce.c"
  ],
  "entropy": 0.8812908992306927
 },
 "b0bd35e622ffbda2c01dc67a0381c6a18817a29a": {
  "num_adds_if": 0,
  "num_dels_if": 0,
  "num_mod_total_if": 0,
  "num_adds_loop": 0,
  "num_dels_loop": 1,
  "num_mod_total_loop": 1,
  "file_hash": "b0bd35e622ffbda2c01dc67a0381c6a18817a29a",
  "num_adds": 32,
  "num_dels": 15,
  "num_mod_lns_total": 47,
  "mod_files_lst": [
   "arch/x86_64/Kconfig"
  ],
  "entropy": 0.0
 },
 "efbbdce94f6ea54cf06d9a06e4c95f6874ad64a8": {
  "num_adds_if": 0,
  "num_dels_if": 2,
  "num_mod_total_if": 2,
  "num_adds_loop": 0,
  "num_dels_loop": 0,
  "num_mod_total_loop": 0,
  "file_hash": "efbbdce94f6ea54cf06d9a06e4c95f6874ad64a8",
  "num_adds": 2,
  "num_dels": 15,
  "num_mod_lns_total": 17,
  "mod_files_lst": [
   "arch/x86_64/kernel/sys_x86_64.c",
   "include/asm-x86_64/unistd.h"
  ],
  "entropy": 0.6722948170756379
 },
 "bf0f2e23834e2bf7d64b467ef07095b1c7e2c04b": {
  "num_adds_if": 0,
  "num_dels_if": 0,
  "num_mod_total_if": 0,
  "num_adds_loop": 0,
  "num_dels_loop": 0,
  "num_mod_total_loop": 0,
  "file_hash": "bf0f2e23834e2bf7d64b467ef07095b1c7e2c04b",
  "num_adds": 1,
  "num_dels": 1,
  "num_mod_lns_total": 2,
  "mod_files_lst": [
   "include/asm-x86_64/cache.h"
  ],
  "entropy": 0.0
 },
 "8e0d4f4e9132ae6e353f9cf27261627bcc7c65cc": {
  "num_adds_if": 0,
  "num_dels_if": 2,
  "num_mod_total_if": 2,
  "num_adds_loop": 0,
  "num_dels_loop": 0,
  "num_mod_total_loop": 0,
  "file_hash": "8e0d4f4e9132ae6e353f9cf27261627bcc7c65cc",
  "num_adds": 0,
  "num_dels": 283,
  "num_mod_lns_total": 283,
  "mod_files_lst": [
   "include/asm-x86_64/rwsem.h"
  ],
  "entropy": 0.0
 },
 "a5b250a428aabc619ace872f8220a7d0b8f7d557": {
  "num_adds_if": 0,
  "num_dels_if": 0,
  "num_mod_total_if": 0,
  "num_adds_loop": 0,
  "num_dels_loop": 0,
  "num_mod_total_loop": 0,
  "file_hash": "a5b250a428aabc619ace872f8220a7d0b8f7d557",
  "num_adds": 2,
  "num_dels": 310,
  "num_mod_lns_total": 312,
  "mod_files_lst": [
   "arch/x86_64/lib/clear_page.S",
   "arch/x86_64/lib/copy_page.S",
   "arch/x86_64/lib/memcpy.S",
   "arch/x86_64/lib/memset.S"
  ],
  "entropy": 1.9256892344377599
 },
 "a6f5deb2be4c82f24fefadcbf7e448f540c05ae6": {
  "num_adds_if": 0,
  "num_dels_if": 0,
  "num_mod_total_if": 0,
  "num_adds_loop": 2,
  "num_dels_loop": 2,
  "num_mod_total_loop": 4,
  "file_hash": "a6f5deb2be4c82f24fefadcbf7e448f540c05ae6",
  "num_adds": 2,
  "num_dels": 2,
  "num_mod_lns_total": 4,
  "mod_files_lst": [
   "arch/x86_64/kernel/reboot.c",
   "include/asm-i386/mach-default/mach_reboot.h"
  ],
  "entropy": 1.0
 },
 "2b0918758dd68d6b8d01318a5200b65b9209760d": {
  "num_adds_if": 1,
  "num_dels_if": 2,
  "num_mod_total_if": 3,
  "num_adds_loop": 1,
  "num_dels_loop": 1,
  "num_mod_total_loop": 2,
  "file_hash": "2b0918758dd68d6b8d01318a5200b65b9209760d",
  "num_adds": 32,
  "num_dels": 14,
  "num_mod_lns_total": 46,
  "mod_files_lst": [
   "arch/i386/kernel/cpu/intel_cacheinfo.c"
  ],
  "entropy": 0.0
 },
 "94605eff572b727aaad9b4b29bc358b919096503": {
  "num_adds_if": 24,
  "num_dels_if": 21,
  "num_mod_total_if": 45,
  "num_adds_loop": 2,
  "num_dels_loop": 8,
  "num_mod_total_loop": 10,
  "file_hash": "94605eff572b727aaad9b4b29bc358b919096503",
  "num_adds": 178,
  "num_dels": 110,
  "num_mod_lns_total": 288,
  "mod_files_lst": [
   "arch/i386/kernel/cpu/amd.c",
   "arch/i386/kernel/cpu/common.c",
   "arch/i386/kernel/cpu/intel.c",
   "arch/i386/kernel/cpu/intel_cacheinfo.c",
   "arch/i386/kernel/cpu/proc.c",
   "arch/i386/kernel/smpboot.c",
   "arch/x86_64/kernel/setup.c",
   "arch/x86_64/kernel/smpboot.c",
   "include/asm-i386/processor.h",
   "include/asm-x86_64/processor.h",
   "include/linux/bitops.h"
  ],
  "entropy": 2.6253375594371646
 },
 "e90f22edf432512219cc2952f5811961abbd164f": {
  "num_adds_if": 0,
  "num_dels_if": 0,
  "num_mod_total_if": 0,
  "num_adds_loop": 0,
  "num_dels_loop": 0,
  "num_mod_total_loop": 0,
  "file_hash": "e90f22edf432512219cc2952f5811961abbd164f",
  "num_adds": 2,
  "num_dels": 3,
  "num_mod_lns_total": 5,
  "mod_files_lst": [
   "include/asm-x86_64/mmzone.h"
  ],
  "entropy": 0.0
 },
 "3506229ff9968e5dbc862a50285fbea0e8821b58": {
  "num_adds_if": 0,
  "num_dels_if": 0,
  "num_mod_total_if": 0,
  "num_adds_loop": 0,
  "num_dels_loop": 0,
  "num_mod_total_loop": 0,
  "file_hash": "3506229ff9968e5dbc862a50285fbea0e8821b58",
  "num_adds": 6,
  "num_dels": 4,
  "num_mod_lns_total": 10,
  "mod_files_lst": [
   "arch/x86_64/kernel/reboot.c",
   "arch/x86_64/kernel/smp.c"
  ],
  "entropy": 1.0
 },
 "a88cde13bae3fffd6ecc812bdd02c91eafb6073e": {
  "num_adds_if": 5,
  "num_dels_if": 5,
  "num_mod_total_if": 10,
  "num_adds_loop": 0,
  "num_dels_loop": 0,
  "num_mod_total_loop": 0,
  "file_hash": "a88cde13bae3fffd6ecc812bdd02c91eafb6073e",
  "num_adds": 28,
  "num_dels": 21,
  "num_mod_lns_total": 49,
  "mod_files_lst": [
   "arch/x86_64/kernel/process.c",
   "include/asm-x86_64/msr.h"
  ],
  "entropy": 0.2460225782203316
 },
 "ea0be473a1f0ee89024a24d8ea4b05fbf6efcee3": {
  "num_adds_if": 0,
  "num_dels_if": 0,
  "num_mod_total_if": 0,
  "num_adds_loop": 0,
  "num_dels_loop": 0,
  "num_mod_total_loop": 0,
  "file_hash": "ea0be473a1f0ee89024a24d8ea4b05fbf6efcee3",
  "num_adds": 12,
  "num_dels": 5,
  "num_mod_lns_total": 17,
  "mod_files_lst": [
   "arch/x86_64/Kconfig",
   "arch/x86_64/ia32/ia32_aout.c",
   "arch/x86_64/ia32/ia32_binfmt.c",
   "arch/x86_64/kernel/x8664_ksyms.c",
   "include/asm-x86_64/ia32.h"
  ],
  "entropy": 2.256908989558354
 },
 "af9c142de94ecf724a18700273bbba390873e072": {
  "num_adds_if": 0,
  "num_dels_if": 0,
  "num_mod_total_if": 0,
  "num_adds_loop": 0,
  "num_dels_loop": 0,
  "num_mod_total_loop": 0,
  "file_hash": "af9c142de94ecf724a18700273bbba390873e072",
  "num_adds": 13,
  "num_dels": 0,
  "num_mod_lns_total": 13,
  "mod_files_lst": [
   "arch/i386/kernel/cpu/mtrr/main.c",
   "arch/x86_64/kernel/setup.c"
  ],
  "entropy": 0.9612366047228759
 },
 "1d2e6bd86152ab86fb866555281869df340e6c6a": {
  "num_adds_if": 0,
  "num_dels_if": 0,
  "num_mod_total_if": 0,
  "num_adds_loop": 0,
  "num_dels_loop": 0,
  "num_mod_total_loop": 0,
  "file_hash": "1d2e6bd86152ab86fb866555281869df340e6c6a",
  "num_adds": 3,
  "num_dels": 2,
  "num_mod_lns_total": 5,
  "mod_files_lst": [
   "drivers/char/agp/amd64-agp.c"
  ],
  "entropy": 0.0
 },
 "172efbb40333d0ca10ebaab11a98f9be687bee39": {
  "num_adds_if": 0,
  "num_dels_if": 0,
  "num_mod_total_if": 0,
  "num_adds_loop": 0,
  "num_dels_loop": 0,
  "num_mod_total_loop": 0,
  "file_hash": "172efbb40333d0ca10ebaab11a98f9be687bee39",
  "num_adds": 1,
  "num_dels": 1,
  "num_mod_lns_total": 2,
  "mod_files_lst": [
   "drivers/char/agp/amd64-agp.c"
  ],
  "entropy": 0.0
 },
 "870b7681cd3f867c1ffc8d7fbe9b22216e73a536": {
  "num_adds_if": 0,
  "num_dels_if": 0,
  "num_mod_total_if": 0,
  "num_adds_loop": 0,
  "num_dels_loop": 0,
  "num_mod_total_loop": 0,
  "file_hash": "870b7681cd3f867c1ffc8d7fbe9b22216e73a536",
  "num_adds": 10,
  "num_dels": 0,
  "num_mod_lns_total": 10,
  "mod_files_lst": [
   "drivers/char/agp/amd64-agp.c"
  ],
  "entropy": 0.0
 },
 "529a340402e419f935d411ce0a085e96fcaf3872": {
  "num_adds_if": 6,
  "num_dels_if": 3,
  "num_mod_total_if": 9,
  "num_adds_loop": 2,
  "num_dels_loop": 2,
  "num_mod_total_loop": 4,
  "file_hash": "529a340402e419f935d411ce0a085e96fcaf3872",
  "num_adds": 43,
  "num_dels": 24,
  "num_mod_lns_total": 67,
  "mod_files_lst": [
   "arch/x86_64/mm/numa.c"
  ],
  "entropy": 0.0
 },
 "e4e5d324b9c5586f408a72d1534474c449dd5212": {
  "num_adds_if": 0,
  "num_dels_if": 0,
  "num_mod_total_if": 0,
  "num_adds_loop": 0,
  "num_dels_loop": 0,
  "num_mod_total_loop": 0,
  "file_hash": "e4e5d324b9c5586f408a72d1534474c449dd5212",
  "num_adds": 17,
  "num_dels": 0,
  "num_mod_lns_total": 17,
  "mod_files_lst": [
   "arch/x86_64/kernel/signal.c"
  ],
  "entropy": 0.0
 },
 "420f8f68c9c5148dddf946bebdbc7eacde2172cb": {
  "num_adds_if": 5,
  "num_dels_if": 1,
  "num_mod_total_if": 6,
  "num_adds_loop": 1,
  "num_dels_loop": 1,
  "num_mod_total_loop": 2,
  "file_hash": "420f8f68c9c5148dddf946bebdbc7eacde2172cb",
  "num_adds": 47,
  "num_dels": 5,
  "num_mod_lns_total": 52,
  "mod_files_lst": [
   "Documentation/x86_64/boot-options.txt",
   "arch/x86_64/kernel/mpparse.c",
   "arch/x86_64/kernel/smpboot.c",
   "include/asm-x86_64/smp.h"
  ],
  "entropy": 1.1449479097220314
 },
 "485832a5d928facd82f1525270d9f048da2063a1": {
  "num_adds_if": 0,
  "num_dels_if": 0,
  "num_mod_total_if": 0,
  "num_adds_loop": 0,
  "num_dels_loop": 0,
  "num_mod_total_loop": 0,
  "file_hash": "485832a5d928facd82f1525270d9f048da2063a1",
  "num_adds": 6,
  "num_dels": 6,
  "num_mod_lns_total": 12,
  "mod_files_lst": [
   "include/asm-x86_64/spinlock.h"
  ],
  "entropy": 0.0
 },
 "8315eca25583c369e28f48909d3341dc21d6214d": {
  "num_adds_if": 0,
  "num_dels_if": 0,
  "num_mod_total_if": 0,
  "num_adds_loop": 0,
  "num_dels_loop": 0,
  "num_mod_total_loop": 0,
  "file_hash": "8315eca25583c369e28f48909d3341dc21d6214d",
  "num_adds": 5,
  "num_dels": 1,
  "num_mod_lns_total": 6,
  "mod_files_lst": [
   "Documentation/x86_64/mm.txt"
  ],
  "entropy": 0.0
 },
 "59170891049cc469777a392e0b3f5aa7aad784a6": {
  "num_adds_if": 0,
  "num_dels_if": 0,
  "num_mod_total_if": 0,
  "num_adds_loop": 0,
  "num_dels_loop": 0,
  "num_mod_total_loop": 0,
  "file_hash": "59170891049cc469777a392e0b3f5aa7aad784a6",
  "num_adds": 1,
  "num_dels": 4,
  "num_mod_lns_total": 5,
  "mod_files_lst": [
   "arch/x86_64/mm/init.c"
  ],
  "entropy": 0.0
 },
 "4d74dbd79a571b31f7cd2c69bb5e44368972bf93": {
  "num_adds_if": 0,
  "num_dels_if": 0,
  "num_mod_total_if": 0,
  "num_adds_loop": 0,
  "num_dels_loop": 0,
  "num_mod_total_loop": 0,
  "file_hash": "4d74dbd79a571b31f7cd2c69bb5e44368972bf93",
  "num_adds": 0,
  "num_dels": 2,
  "num_mod_lns_total": 2,
  "mod_files_lst": [
   "arch/x86_64/mm/init.c"
  ],
  "entropy": 0.0
 },
 "2bc0414ee04fd8bb798760801f5d7476dff44241": {
  "num_adds_if": 0,
  "num_dels_if": 0,
  "num_mod_total_if": 0,
  "num_adds_loop": 0,
  "num_dels_loop": 0,
  "num_mod_total_loop": 0,
  "file_hash": "2bc0414ee04fd8bb798760801f5d7476dff44241",
  "num_adds": 8,
  "num_dels": 16,
  "num_mod_lns_total": 24,
  "mod_files_lst": [
   "arch/x86_64/kernel/e820.c",
   "arch/x86_64/kernel/head64.c",
   "arch/x86_64/kernel/setup.c",
   "arch/x86_64/kernel/vmlinux.lds.S",
   "arch/x86_64/mm/init.c",
   "include/asm-generic/sections.h"
  ],
  "entropy": 2.1897981900809884
 },
 "6b75aeedde1e8a8513393d3c1367bf81bc5b0c67": {
  "num_adds_if": 0,
  "num_dels_if": 0,
  "num_mod_total_if": 0,
  "num_adds_loop": 0,
  "num_dels_loop": 0,
  "num_mod_total_loop": 0,
  "file_hash": "6b75aeedde1e8a8513393d3c1367bf81bc5b0c67",
  "num_adds": 3,
  "num_dels": 3,
  "num_mod_lns_total": 6,
  "mod_files_lst": [
   "include/asm-x86_64/page.h",
   "include/asm-x86_64/pgtable.h"
  ],
  "entropy": 0.9182958340544896
 },
 "f6c2e3330d3fdd5474bc3756da46fca889a30e33": {
  "num_adds_if": 3,
  "num_dels_if": 2,
  "num_mod_total_if": 5,
  "num_adds_loop": 0,
  "num_dels_loop": 0,
  "num_mod_total_loop": 0,
  "file_hash": "f6c2e3330d3fdd5474bc3756da46fca889a30e33",
  "num_adds": 56,
  "num_dels": 32,
  "num_mod_lns_total": 88,
  "mod_files_lst": [
   "arch/i386/kernel/acpi/boot.c",
   "arch/x86_64/kernel/head.S",
   "arch/x86_64/kernel/head64.c",
   "arch/x86_64/kernel/mpparse.c",
   "arch/x86_64/kernel/setup.c",
   "arch/x86_64/kernel/setup64.c",
   "arch/x86_64/kernel/smpboot.c",
   "arch/x86_64/mm/init.c",
   "include/asm-x86_64/pgtable.h",
   "include/asm-x86_64/proto.h",
   "include/asm-x86_64/smp.h"
  ],
  "entropy": 2.299083893091303
 },
 "69d81fcde7797342417591ba7affb372b9c86eae": {
  "num_adds_if": 0,
  "num_dels_if": 0,
  "num_mod_total_if": 0,
  "num_adds_loop": 0,
  "num_dels_loop": 0,
  "num_mod_total_loop": 0,
  "file_hash": "69d81fcde7797342417591ba7affb372b9c86eae",
  "num_adds": 18,
  "num_dels": 5,
  "num_mod_lns_total": 23,
  "mod_files_lst": [
   "arch/x86_64/kernel/setup.c",
   "arch/x86_64/mm/numa.c",
   "arch/x86_64/mm/srat.c",
   "include/asm-x86_64/numa.h",
   "include/asm-x86_64/pda.h",
   "include/asm-x86_64/topology.h",
   "include/linux/mmzone.h"
  ],
  "entropy": 2.383593219149464
 },
 "50895c5d76e15d8af480eff1aaab5770cabbc2c2": {
  "num_adds_if": 0,
  "num_dels_if": 0,
  "num_mod_total_if": 0,
  "num_adds_loop": 0,
  "num_dels_loop": 0,
  "num_mod_total_loop": 0,
  "file_hash": "50895c5d76e15d8af480eff1aaab5770cabbc2c2",
  "num_adds": 1,
  "num_dels": 1,
  "num_mod_lns_total": 2,
  "mod_files_lst": [
   "arch/x86_64/kernel/aperture.c"
  ],
  "entropy": 0.0
 },
 "f5f786d0455c359c554b8f74783f887c0a2c9fac": {
  "num_adds_if": 4,
  "num_dels_if": 2,
  "num_mod_total_if": 6,
  "num_adds_loop": 0,
  "num_dels_loop": 0,
  "num_mod_total_loop": 0,
  "file_hash": "f5f786d0455c359c554b8f74783f887c0a2c9fac",
  "num_adds": 4,
  "num_dels": 4,
  "num_mod_lns_total": 8,
  "mod_files_lst": [
   "arch/i386/kernel/cpu/common.c",
   "arch/x86_64/kernel/setup.c"
  ],
  "entropy": 1.0
 },
 "e9b59d834faf0305cb6214a358f65f72c57b9e99": {
  "num_adds_if": 0,
  "num_dels_if": 0,
  "num_mod_total_if": 0,
  "num_adds_loop": 0,
  "num_dels_loop": 0,
  "num_mod_total_loop": 0,
  "file_hash": "e9b59d834faf0305cb6214a358f65f72c57b9e99",
  "num_adds": 0,
  "num_dels": 2,
  "num_mod_lns_total": 2,
  "mod_files_lst": [
   "arch/x86_64/kernel/smp.c"
  ],
  "entropy": 0.0
 },
 "47492d3667ec519172ab978bd8231b8c7152fa9d": {
  "num_adds_if": 1,
  "num_dels_if": 0,
  "num_mod_total_if": 1,
  "num_adds_loop": 0,
  "num_dels_loop": 0,
  "num_mod_total_loop": 0,
  "file_hash": "47492d3667ec519172ab978bd8231b8c7152fa9d",
  "num_adds": 7,
  "num_dels": 1,
  "num_mod_lns_total": 8,
  "mod_files_lst": [
   "arch/x86_64/kernel/pci-gart.c"
  ],
  "entropy": 0.0
 },
 "07808b74e7dab1aa385e698795875337d72daf7d": {
  "num_adds_if": 0,
  "num_dels_if": 0,
  "num_mod_total_if": 0,
  "num_adds_loop": 0,
  "num_dels_loop": 0,
  "num_mod_total_loop": 0,
  "file_hash": "07808b74e7dab1aa385e698795875337d72daf7d",
  "num_adds": 5,
  "num_dels": 11,
  "num_mod_lns_total": 16,
  "mod_files_lst": [
   "include/linux/mm.h",
   "include/linux/mmzone.h",
   "mm/filemap.c",
   "mm/page_alloc.c"
  ],
  "entropy": 1.5487949406953985
 },
 "1dff7f3db5f045ccbfeca5bb00b0958a78501557": {
  "num_adds_if": 0,
  "num_dels_if": 0,
  "num_mod_total_if": 0,
  "num_adds_loop": 0,
  "num_dels_loop": 0,
  "num_mod_total_loop": 0,
  "file_hash": "1dff7f3db5f045ccbfeca5bb00b0958a78501557",
  "num_adds": 1,
  "num_dels": 3,
  "num_mod_lns_total": 4,
  "mod_files_lst": [
   "include/asm-x86_64/mmzone.h"
  ],
  "entropy": 0.0
 },
 "6004e1b7effcbb385a6b7c790e4b8008682cf679": {
  "num_adds_if": 8,
  "num_dels_if": 3,
  "num_mod_total_if": 11,
  "num_adds_loop": 2,
  "num_dels_loop": 0,
  "num_mod_total_loop": 2,
  "file_hash": "6004e1b7effcbb385a6b7c790e4b8008682cf679",
  "num_adds": 86,
  "num_dels": 17,
  "num_mod_lns_total": 103,
  "mod_files_lst": [
   "arch/i386/kernel/acpi/boot.c",
   "arch/x86_64/kernel/io_apic.c",
   "arch/x86_64/kernel/mpparse.c",
   "include/asm-x86_64/desc.h",
   "include/asm-x86_64/mpspec.h"
  ],
  "entropy": 1.0955550754410466
 },
 "89b831ef8bf5cfbb357dbc0a2e07700d7f20eec5": {
  "num_adds_if": 33,
  "num_dels_if": 0,
  "num_mod_total_if": 33,
  "num_adds_loop": 6,
  "num_dels_loop": 0,
  "num_mod_total_loop": 6,
  "file_hash": "89b831ef8bf5cfbb357dbc0a2e07700d7f20eec5",
  "num_adds": 582,
  "num_dels": 1,
  "num_mod_lns_total": 583,
  "mod_files_lst": [
   "arch/x86_64/Kconfig",
   "arch/x86_64/kernel/Makefile",
   "arch/x86_64/kernel/apic.c",
   "arch/x86_64/kernel/entry.S",
   "arch/x86_64/kernel/i8259.c",
   "arch/x86_64/kernel/mce.c",
   "arch/x86_64/kernel/mce_amd.c",
   "arch/x86_64/kernel/traps.c",
   "include/asm-x86_64/apic.h",
   "include/asm-x86_64/hw_irq.h",
   "include/asm-x86_64/mce.h"
  ],
  "entropy": 0.6206366564637247
 },
 "979edfadbae2286eec5b46143c00e81bca96498e": {
  "num_adds_if": 0,
  "num_dels_if": 0,
  "num_mod_total_if": 0,
  "num_adds_loop": 0,
  "num_dels_loop": 0,
  "num_mod_total_loop": 0,
  "file_hash": "979edfadbae2286eec5b46143c00e81bca96498e",
  "num_adds": 21,
  "num_dels": 14,
  "num_mod_lns_total": 35,
  "mod_files_lst": [
   "include/asm-x86_64/hpet.h"
  ],
  "entropy": 0.0
 },
 "e18c6874a505958d153a11f9d6947971c349008a": {
  "num_adds_if": 3,
  "num_dels_if": 0,
  "num_mod_total_if": 3,
  "num_adds_loop": 1,
  "num_dels_loop": 0,
  "num_mod_total_loop": 1,
  "file_hash": "e18c6874a505958d153a11f9d6947971c349008a",
  "num_adds": 19,
  "num_dels": 0,
  "num_mod_lns_total": 19,
  "mod_files_lst": [
   "arch/x86_64/mm/init.c"
  ],
  "entropy": 0.0
 },
 "b0d41693217b3bb5b837940dc7465e82a9d49476": {
  "num_adds_if": 0,
  "num_dels_if": 0,
  "num_mod_total_if": 0,
  "num_adds_loop": 0,
  "num_dels_loop": 0,
  "num_mod_total_loop": 0,
  "file_hash": "b0d41693217b3bb5b837940dc7465e82a9d49476",
  "num_adds": 1,
  "num_dels": 2,
  "num_mod_lns_total": 3,
  "mod_files_lst": [
   "mm/page_alloc.c"
  ],
  "entropy": 0.0
 },
 "fed644132f8ec4bf05b63f79c507c0acaa692c37": {
  "num_adds_if": 0,
  "num_dels_if": 0,
  "num_mod_total_if": 0,
  "num_adds_loop": 0,
  "num_dels_loop": 0,
  "num_mod_total_loop": 0,
  "file_hash": "fed644132f8ec4bf05b63f79c507c0acaa692c37",
  "num_adds": 2,
  "num_dels": 2,
  "num_mod_lns_total": 4,
  "mod_files_lst": [
   "arch/i386/kernel/srat.c"
  ],
  "entropy": 0.0
 },
 "d1e3dfdc2c934a279bcfa19359e4daec02bda18f": {
  "num_adds_if": 0,
  "num_dels_if": 0,
  "num_mod_total_if": 0,
  "num_adds_loop": 0,
  "num_dels_loop": 0,
  "num_mod_total_loop": 0,
  "file_hash": "d1e3dfdc2c934a279bcfa19359e4daec02bda18f",
  "num_adds": 4,
  "num_dels": 0,
  "num_mod_lns_total": 4,
  "mod_files_lst": [
   "arch/ia64/Kconfig"
  ],
  "entropy": 0.0
 },
 "a2f1b424900715ed9d1699c3bb88a434a2b42bc0": {
  "num_adds_if": 7,
  "num_dels_if": 3,
  "num_mod_total_if": 10,
  "num_adds_loop": 4,
  "num_dels_loop": 1,
  "num_mod_total_loop": 5,
  "file_hash": "a2f1b424900715ed9d1699c3bb88a434a2b42bc0",
  "num_adds": 90,
  "num_dels": 55,
  "num_mod_lns_total": 145,
  "mod_files_lst": [
   "arch/x86_64/mm/init.c",
   "arch/x86_64/mm/numa.c",
   "include/asm-x86_64/dma.h",
   "include/asm-x86_64/proto.h",
   "include/linux/gfp.h",
   "include/linux/mmzone.h",
   "mm/page_alloc.c"
  ],
  "entropy": 2.2953493166675827
 },
 "56720367cd89ef5265f39da2d674c5b92cd4cd87": {
  "num_adds_if": 0,
  "num_dels_if": 0,
  "num_mod_total_if": 0,
  "num_adds_loop": 0,
  "num_dels_loop": 0,
  "num_mod_total_loop": 0,
  "file_hash": "56720367cd89ef5265f39da2d674c5b92cd4cd87",
  "num_adds": 83,
  "num_dels": 15,
  "num_mod_lns_total": 98,
  "mod_files_lst": [
   "arch/x86_64/defconfig"
  ],
  "entropy": 0.0
 },
 "0174f72f848dfe7dc7488799776303c81b181b16": {
  "num_adds_if": 23,
  "num_dels_if": 407,
  "num_mod_total_if": 430,
  "num_adds_loop": 4,
  "num_dels_loop": 131,
  "num_mod_total_loop": 135,
  "file_hash": "0174f72f848dfe7dc7488799776303c81b181b16",
  "num_adds": 868,
  "num_dels": 11066,
  "num_mod_lns_total": 11934,
  "mod_files_lst": [
   "arch/powerpc/Kconfig",
   "arch/powerpc/Makefile",
   "arch/powerpc/configs/pseries_defconfig",
   "arch/powerpc/kernel/Makefile",
   "arch/powerpc/kernel/asm-offsets.c",
   "arch/powerpc/kernel/irq.c",
   "arch/powerpc/kernel/lparcfg.c",
   "arch/powerpc/kernel/machine_kexec_64.c",
   "arch/powerpc/kernel/prom.c",
   "arch/powerpc/kernel/rtas-rtc.c",
   "arch/powerpc/kernel/setup_32.c",
   "arch/powerpc/kernel/setup_64.c",
   "arch/powerpc/kernel/signal_32.c",
   "arch/powerpc/kernel/signal_64.c",
   "arch/powerpc/kernel/vdso32/datapage.S",
   "arch/powerpc/kernel/vdso32/gettimeofday.S",
   "arch/powerpc/kernel/vdso64/datapage.S",
   "arch/powerpc/kernel/vdso64/gettimeofday.S",
   "arch/powerpc/platforms/iseries/irq.c",
   "arch/powerpc/platforms/iseries/setup.c",
   "arch/powerpc/platforms/powermac/time.c",
   "arch/powerpc/platforms/pseries/Makefile",
   "arch/powerpc/platforms/pseries/setup.c",
   "arch/ppc64/Kconfig",
   "arch/ppc64/kernel/Makefile",
   "arch/ppc64/kernel/asm-offsets.c",
   "arch/ppc64/kernel/btext.c",
   "arch/ppc64/kernel/head.S",
   "arch/ppc64/kernel/misc.S",
   "arch/ppc64/kernel/ppc_ksyms.c",
   "arch/ppc64/kernel/prom.c",
   "arch/ppc64/kernel/prom_init.c",
   "arch/ppc64/kernel/rtc.c",
   "arch/ppc64/kernel/semaphore.c",
   "arch/ppc64/kernel/vdso.c",
   "arch/ppc64/kernel/vmlinux.lds.S",
   "arch/ppc64/xmon/privinst.h",
   "drivers/char/Kconfig",
   "include/asm-powerpc/delay.h",
   "include/asm-powerpc/floppy.h",
   "include/asm-powerpc/kexec.h",
   "include/asm-powerpc/machdep.h",
   "include/asm-powerpc/nvram.h",
   "include/asm-powerpc/page.h",
   "include/asm-powerpc/page_32.h",
   "include/asm-powerpc/page_64.h",
   "include/asm-powerpc/serial.h",
   "include/asm-powerpc/vdso_datapage.h",
   "include/asm-ppc/nvram.h",
   "include/asm-ppc64/page.h",
   "include/asm-ppc64/prom.h",
   "include/asm-ppc64/system.h"
  ],
  "entropy": 3.8762431723415443
 },
 "302fe1758d85ad9c868e77625f61b7edad106381": {
  "num_adds_if": 0,
  "num_dels_if": 0,
  "num_mod_total_if": 0,
  "num_adds_loop": 0,
  "num_dels_loop": 0,
  "num_mod_total_loop": 0,
  "file_hash": "302fe1758d85ad9c868e77625f61b7edad106381",
  "num_adds": 2,
  "num_dels": 0,
  "num_mod_lns_total": 2,
  "mod_files_lst": [
   "net/ipv6/netfilter/nf_conntrack_reasm.c"
  ],
  "entropy": 0.0
 },
 "1ba430bc3e243d38c0bb2b185bea664b04fc59df": {
  "num_adds_if": 3,
  "num_dels_if": 1,
  "num_mod_total_if": 4,
  "num_adds_loop": 1,
  "num_dels_loop": 1,
  "num_mod_total_loop": 2,
  "file_hash": "1ba430bc3e243d38c0bb2b185bea664b04fc59df",
  "num_adds": 26,
  "num_dels": 16,
  "num_mod_lns_total": 42,
  "mod_files_lst": [
   "net/ipv6/netfilter/nf_conntrack_reasm.c"
  ],
  "entropy": 0.0
 },
 "7686a02c0ebc11e4f881fe14db3df18569b7dbc1": {
  "num_adds_if": 0,
  "num_dels_if": 0,
  "num_mod_total_if": 0,
  "num_adds_loop": 0,
  "num_dels_loop": 0,
  "num_mod_total_loop": 0,
  "file_hash": "7686a02c0ebc11e4f881fe14db3df18569b7dbc1",
  "num_adds": 7,
  "num_dels": 7,
  "num_mod_lns_total": 14,
  "mod_files_lst": [
   "net/ipv6/netfilter/nf_conntrack_l3proto_ipv6.c",
   "net/ipv6/netfilter/nf_conntrack_reasm.c"
  ],
  "entropy": 0.9852281360342515
 },
 "9bdf87d90bbd1a3e3183ac116a6a9d861f32baca": {
  "num_adds_if": 0,
  "num_dels_if": 0,
  "num_mod_total_if": 0,
  "num_adds_loop": 1,
  "num_dels_loop": 2,
  "num_mod_total_loop": 3,
  "file_hash": "9bdf87d90bbd1a3e3183ac116a6a9d861f32baca",
  "num_adds": 14,
  "num_dels": 36,
  "num_mod_lns_total": 50,
  "mod_files_lst": [
   "net/ipv6/netfilter/Kconfig"
  ],
  "entropy": 0.0
 },
 "47d4305bf2275f82a51fa025257c2c1996356d6b": {
  "num_adds_if": 0,
  "num_dels_if": 0,
  "num_mod_total_if": 0,
  "num_adds_loop": 0,
  "num_dels_loop": 0,
  "num_mod_total_loop": 0,
  "file_hash": "47d4305bf2275f82a51fa025257c2c1996356d6b",
  "num_adds": 1,
  "num_dels": 1,
  "num_mod_lns_total": 2,
  "mod_files_lst": [
   "net/Makefile"
  ],
  "entropy": 0.0
 },
 "37d2e7a20d745035b600f1a6be56cbb9c7259419": {
  "num_adds_if": 1,
  "num_dels_if": 1,
  "num_mod_total_if": 2,
  "num_adds_loop": 0,
  "num_dels_loop": 1,
  "num_mod_total_loop": 1,
  "file_hash": "37d2e7a20d745035b600f1a6be56cbb9c7259419",
  "num_adds": 24,
  "num_dels": 41,
  "num_mod_lns_total": 65,
  "mod_files_lst": [
   "include/linux/netfilter/nfnetlink.h",
   "net/ipv4/netfilter/ip_conntrack_netlink.c",
   "net/netfilter/nfnetlink.c",
   "net/netfilter/nfnetlink_log.c",
   "net/netfilter/nfnetlink_queue.c"
  ],
  "entropy": 1.854926217439614
 },
 "3746a2b1402e7933c7f1eabdce384b8454dc2ef7": {
  "num_adds_if": 1,
  "num_dels_if": 0,
  "num_mod_total_if": 1,
  "num_adds_loop": 0,
  "num_dels_loop": 0,
  "num_mod_total_loop": 0,
  "file_hash": "3746a2b1402e7933c7f1eabdce384b8454dc2ef7",
  "num_adds": 6,
  "num_dels": 0,
  "num_mod_lns_total": 6,
  "mod_files_lst": [
   "net/netfilter/nf_conntrack_proto_tcp.c"
  ],
  "entropy": 0.0
 },
 "56558208521729fa6b2a0f12df22e1569dee297a": {
  "num_adds_if": 8,
  "num_dels_if": 0,
  "num_mod_total_if": 8,
  "num_adds_loop": 0,
  "num_dels_loop": 0,
  "num_mod_total_loop": 0,
  "file_hash": "56558208521729fa6b2a0f12df22e1569dee297a",
  "num_adds": 46,
  "num_dels": 0,
  "num_mod_lns_total": 46,
  "mod_files_lst": [
   "net/ipv4/netfilter/ip_conntrack_netlink.c",
   "net/ipv4/netfilter/ip_conntrack_proto_tcp.c"
  ],
  "entropy": 0.6152538910563408
 },
 "c0400c4f5a08cfd1c657f7f616fcf1dfbd76a4d7": {
  "num_adds_if": 1,
  "num_dels_if": 0,
  "num_mod_total_if": 1,
  "num_adds_loop": 1,
  "num_dels_loop": 1,
  "num_mod_total_loop": 2,
  "file_hash": "c0400c4f5a08cfd1c657f7f616fcf1dfbd76a4d7",
  "num_adds": 4,
  "num_dels": 1,
  "num_mod_lns_total": 5,
  "mod_files_lst": [
   "include/linux/netfilter/nfnetlink.h"
  ],
  "entropy": 0.0
 },
 "dbd36ea496726460299842fdbeaaa7fff2f0c5c7": {
  "num_adds_if": 0,
  "num_dels_if": 0,
  "num_mod_total_if": 0,
  "num_adds_loop": 0,
  "num_dels_loop": 0,
  "num_mod_total_loop": 0,
  "file_hash": "dbd36ea496726460299842fdbeaaa7fff2f0c5c7",
  "num_adds": 3,
  "num_dels": 3,
  "num_mod_lns_total": 6,
  "mod_files_lst": [
   "net/ipv4/netfilter/ip_conntrack_netlink.c"
  ],
  "entropy": 0.0
 },
 "1c24a412fd8873bcacba7ed8a1780d12b86b6cb5": {
  "num_adds_if": 0,
  "num_dels_if": 0,
  "num_mod_total_if": 0,
  "num_adds_loop": 0,
  "num_dels_loop": 0,
  "num_mod_total_loop": 0,
  "file_hash": "1c24a412fd8873bcacba7ed8a1780d12b86b6cb5",
  "num_adds": 7,
  "num_dels": 33,
  "num_mod_lns_total": 40,
  "mod_files_lst": [
   "drivers/scsi/ata_piix.c"
  ],
  "entropy": 0.0
 },
 "e74ac79956ecb56e71a398c57eb10fab8c58a562": {
  "num_adds_if": 0,
  "num_dels_if": 0,
  "num_mod_total_if": 0,
  "num_adds_loop": 0,
  "num_dels_loop": 0,
  "num_mod_total_loop": 0,
  "file_hash": "e74ac79956ecb56e71a398c57eb10fab8c58a562",
  "num_adds": 0,
  "num_dels": 2,
  "num_mod_lns_total": 2,
  "mod_files_lst": [
   "include/linux/libata.h"
  ],
  "entropy": 0.0
 },
 "c6e6e666cbfe40f0d7fb1a293ff6332973acac37": {
  "num_adds_if": 3,
  "num_dels_if": 3,
  "num_mod_total_if": 6,
  "num_adds_loop": 0,
  "num_dels_loop": 0,
  "num_mod_total_loop": 0,
  "file_hash": "c6e6e666cbfe40f0d7fb1a293ff6332973acac37",
  "num_adds": 43,
  "num_dels": 58,
  "num_mod_lns_total": 101,
  "mod_files_lst": [
   "drivers/scsi/libata-core.c",
   "drivers/scsi/libata-scsi.c",
   "drivers/scsi/libata.h"
  ],
  "entropy": 0.8893990149940922
 },
 "2c13b7cee045af689b36349c2bc6a9ed6e3d73fa": {
  "num_adds_if": 2,
  "num_dels_if": 0,
  "num_mod_total_if": 2,
  "num_adds_loop": 0,
  "num_dels_loop": 0,
  "num_mod_total_loop": 0,
  "file_hash": "2c13b7cee045af689b36349c2bc6a9ed6e3d73fa",
  "num_adds": 17,
  "num_dels": 8,
  "num_mod_lns_total": 25,
  "mod_files_lst": [
   "drivers/scsi/libata-core.c",
   "include/linux/libata.h"
  ],
  "entropy": 0.9895875212220556
 },
 "e1410f2d951d45aee3bdbcc05ecedaaa9db276e5": {
  "num_adds_if": 6,
  "num_dels_if": 0,
  "num_mod_total_if": 6,
  "num_adds_loop": 0,
  "num_dels_loop": 0,
  "num_mod_total_loop": 0,
  "file_hash": "e1410f2d951d45aee3bdbcc05ecedaaa9db276e5",
  "num_adds": 26,
  "num_dels": 5,
  "num_mod_lns_total": 31,
  "mod_files_lst": [
   "drivers/scsi/libata-core.c"
  ],
  "entropy": 0.0
 },
 "ad36d1a533da91d3448029b4da1113c5b880f25d": {
  "num_adds_if": 3,
  "num_dels_if": 0,
  "num_mod_total_if": 3,
  "num_adds_loop": 0,
  "num_dels_loop": 0,
  "num_mod_total_loop": 0,
  "file_hash": "ad36d1a533da91d3448029b4da1113c5b880f25d",
  "num_adds": 19,
  "num_dels": 5,
  "num_mod_lns_total": 24,
  "mod_files_lst": [
   "drivers/scsi/ahci.c"
  ],
  "entropy": 0.0
 },
 "493f25ef4087395891c99fcfe2c72e62e293e89f": {
  "num_adds_if": 0,
  "num_dels_if": 0,
  "num_mod_total_if": 0,
  "num_adds_loop": 0,
  "num_dels_loop": 0,
  "num_mod_total_loop": 0,
  "file_hash": "493f25ef4087395891c99fcfe2c72e62e293e89f",
  "num_adds": 2,
  "num_dels": 0,
  "num_mod_lns_total": 2,
  "mod_files_lst": [
   "include/asm-powerpc/page_32.h"
  ],
  "entropy": 0.0
 },
 "5be396b00ca0f2f769c55cf69bbd7c77451c925e": {
  "num_adds_if": 0,
  "num_dels_if": 0,
  "num_mod_total_if": 0,
  "num_adds_loop": 0,
  "num_dels_loop": 0,
  "num_mod_total_loop": 0,
  "file_hash": "5be396b00ca0f2f769c55cf69bbd7c77451c925e",
  "num_adds": 2,
  "num_dels": 2,
  "num_mod_lns_total": 4,
  "mod_files_lst": [
   "arch/powerpc/Kconfig"
  ],
  "entropy": 0.0
 },
 "1dfc6772097ef4eadd39a10ce44557c782d5058e": {
  "num_adds_if": 0,
  "num_dels_if": 0,
  "num_mod_total_if": 0,
  "num_adds_loop": 0,
  "num_dels_loop": 0,
  "num_mod_total_loop": 0,
  "file_hash": "1dfc6772097ef4eadd39a10ce44557c782d5058e",
  "num_adds": 2,
  "num_dels": 0,
  "num_mod_lns_total": 2,
  "mod_files_lst": [
   "arch/powerpc/kernel/prom.c"
  ],
  "entropy": 0.0
 },
 "7568cb4ef6c507164b65b01f972a3bd026898ae1": {
  "num_adds_if": 0,
  "num_dels_if": 374,
  "num_mod_total_if": 374,
  "num_adds_loop": 0,
  "num_dels_loop": 123,
  "num_mod_total_loop": 123,
  "file_hash": "7568cb4ef6c507164b65b01f972a3bd026898ae1",
  "num_adds": 19,
  "num_dels": 9886,
  "num_mod_lns_total": 9905,
  "mod_files_lst": [
   "arch/powerpc/Kconfig",
   "arch/powerpc/kernel/Makefile",
   "arch/powerpc/platforms/pseries/Makefile",
   "arch/ppc64/Kconfig",
   "arch/ppc64/kernel/Makefile",
   "arch/ppc64/kernel/asm-offsets.c",
   "arch/ppc64/kernel/btext.c",
   "arch/ppc64/kernel/head.S",
   "arch/ppc64/kernel/misc.S",
   "arch/ppc64/kernel/ppc_ksyms.c",
   "arch/ppc64/kernel/prom.c",
   "arch/ppc64/kernel/prom_init.c",
   "arch/ppc64/kernel/semaphore.c",
   "arch/ppc64/kernel/vdso.c",
   "arch/ppc64/kernel/vmlinux.lds.S",
   "arch/ppc64/xmon/privinst.h",
   "include/asm-ppc64/page.h"
  ],
  "entropy": 3.095557407115515
 },
 "c55377ee73f6efeb373ae06f6e918d87660b4852": {
  "num_adds_if": 1,
  "num_dels_if": 4,
  "num_mod_total_if": 5,
  "num_adds_loop": 0,
  "num_dels_loop": 4,
  "num_mod_total_loop": 4,
  "file_hash": "c55377ee73f6efeb373ae06f6e918d87660b4852",
  "num_adds": 42,
  "num_dels": 640,
  "num_mod_lns_total": 682,
  "mod_files_lst": [
   "include/asm-powerpc/delay.h",
   "include/asm-powerpc/floppy.h",
   "include/asm-powerpc/nvram.h",
   "include/asm-powerpc/serial.h",
   "include/asm-ppc/nvram.h",
   "include/asm-ppc64/prom.h",
   "include/asm-ppc64/system.h"
  ],
  "entropy": 1.9783309412471866
 },
 "821077b2617ef70662a861393c929d7e47609512": {
  "num_adds_if": 5,
  "num_dels_if": 5,
  "num_mod_total_if": 10,
  "num_adds_loop": 0,
  "num_dels_loop": 0,
  "num_mod_total_loop": 0,
  "file_hash": "821077b2617ef70662a861393c929d7e47609512",
  "num_adds": 33,
  "num_dels": 62,
  "num_mod_lns_total": 95,
  "mod_files_lst": [
   "arch/powerpc/kernel/irq.c",
   "arch/powerpc/kernel/lparcfg.c",
   "arch/powerpc/kernel/setup_32.c",
   "arch/powerpc/platforms/iseries/irq.c",
   "arch/powerpc/platforms/iseries/setup.c"
  ],
  "entropy": 1.7548114272549253
 },
 "d7867959e7e928ab52ef204e2559937e5c9fc4ce": {
  "num_adds_if": 5,
  "num_dels_if": 5,
  "num_mod_total_if": 10,
  "num_adds_loop": 0,
  "num_dels_loop": 0,
  "num_mod_total_loop": 0,
  "file_hash": "d7867959e7e928ab52ef204e2559937e5c9fc4ce",
  "num_adds": 25,
  "num_dels": 32,
  "num_mod_lns_total": 57,
  "mod_files_lst": [
   "arch/powerpc/kernel/lparcfg.c",
   "arch/powerpc/platforms/iseries/setup.c"
  ],
  "entropy": 0.4854607607459134
 },
 "3136254ca5dfaf53486f7032c674f9b6d7fd1d53": {
  "num_adds_if": 8,
  "num_dels_if": 21,
  "num_mod_total_if": 29,
  "num_adds_loop": 3,
  "num_dels_loop": 4,
  "num_mod_total_loop": 7,
  "file_hash": "3136254ca5dfaf53486f7032c674f9b6d7fd1d53",
  "num_adds": 239,
  "num_dels": 437,
  "num_mod_lns_total": 676,
  "mod_files_lst": [
   "arch/powerpc/configs/pseries_defconfig",
   "arch/powerpc/kernel/Makefile",
   "arch/powerpc/kernel/rtas-rtc.c",
   "arch/powerpc/platforms/powermac/time.c",
   "arch/ppc64/kernel/Makefile",
   "arch/ppc64/kernel/rtc.c",
   "drivers/char/Kconfig"
  ],
  "entropy": 1.5138662170287973
 },
 "0c37ec2aa88bd8a6aaeb284ff5c86f4c6d8e8469": {
  "num_adds_if": 0,
  "num_dels_if": 0,
  "num_mod_total_if": 0,
  "num_adds_loop": 0,
  "num_dels_loop": 0,
  "num_mod_total_loop": 0,
  "file_hash": "0c37ec2aa88bd8a6aaeb284ff5c86f4c6d8e8469",
  "num_adds": 39,
  "num_dels": 24,
  "num_mod_lns_total": 63,
  "mod_files_lst": [
   "arch/powerpc/kernel/asm-offsets.c",
   "arch/powerpc/kernel/vdso32/datapage.S",
   "arch/powerpc/kernel/vdso32/gettimeofday.S",
   "arch/powerpc/kernel/vdso64/datapage.S",
   "arch/powerpc/kernel/vdso64/gettimeofday.S",
   "arch/powerpc/platforms/powermac/time.c",
   "include/asm-powerpc/vdso_datapage.h"
  ],
  "entropy": 2.122291064180275
 },
 "50092b233afa96b4c9a4b24ac38199c34e0880cd": {
  "num_adds_if": 0,
  "num_dels_if": 0,
  "num_mod_total_if": 0,
  "num_adds_loop": 0,
  "num_dels_loop": 0,
  "num_mod_total_loop": 0,
  "file_hash": "50092b233afa96b4c9a4b24ac38199c34e0880cd",
  "num_adds": 1,
  "num_dels": 1,
  "num_mod_lns_total": 2,
  "mod_files_lst": [
   "arch/powerpc/Makefile"
  ],
  "entropy": 0.0
 },
 "593e537b93193d1696809817533ce5ad510445b1": {
  "num_adds_if": 2,
  "num_dels_if": 0,
  "num_mod_total_if": 2,
  "num_adds_loop": 0,
  "num_dels_loop": 0,
  "num_mod_total_loop": 0,
  "file_hash": "593e537b93193d1696809817533ce5ad510445b1",
  "num_adds": 57,
  "num_dels": 0,
  "num_mod_lns_total": 57,
  "mod_files_lst": [
   "arch/powerpc/kernel/setup_64.c",
   "arch/ppc64/kernel/machine_kexec.c",
   "include/asm-powerpc/kexec.h"
  ],
  "entropy": 0.5538841735510034
 },
 "c5e24354efae9f962e0e369d875d45f47e0bb9aa": {
  "num_adds_if": 6,
  "num_dels_if": 3,
  "num_mod_total_if": 9,
  "num_adds_loop": 0,
  "num_dels_loop": 0,
  "num_mod_total_loop": 0,
  "file_hash": "c5e24354efae9f962e0e369d875d45f47e0bb9aa",
  "num_adds": 33,
  "num_dels": 9,
  "num_mod_lns_total": 42,
  "mod_files_lst": [
   "arch/powerpc/platforms/pseries/setup.c",
   "arch/ppc64/kernel/machine_kexec.c",
   "include/asm-powerpc/machdep.h"
  ],
  "entropy": 1.2677702161044204
 },
 "5cd16ee934eafca74a6bb790328950cec68a8b78": {
  "num_adds_if": 1,
  "num_dels_if": 0,
  "num_mod_total_if": 1,
  "num_adds_loop": 1,
  "num_dels_loop": 0,
  "num_mod_total_loop": 1,
  "file_hash": "5cd16ee934eafca74a6bb790328950cec68a8b78",
  "num_adds": 391,
  "num_dels": 0,
  "num_mod_lns_total": 391,
  "mod_files_lst": [
   "include/asm-powerpc/page.h",
   "include/asm-powerpc/page_32.h",
   "include/asm-powerpc/page_64.h"
  ],
  "entropy": 1.3626963115814266
 },
 "868accb7b9126dffdebb6b45631e145991e3535d": {
  "num_adds_if": 0,
  "num_dels_if": 0,
  "num_mod_total_if": 0,
  "num_adds_loop": 0,
  "num_dels_loop": 0,
  "num_mod_total_loop": 0,
  "file_hash": "868accb7b9126dffdebb6b45631e145991e3535d",
  "num_adds": 5,
  "num_dels": 5,
  "num_mod_lns_total": 10,
  "mod_files_lst": [
   "arch/powerpc/kernel/irq.c",
   "arch/powerpc/kernel/setup_32.c"
  ],
  "entropy": 0.9709505944546686
 },
 "d9ae2bad5c92cd116e3daedf16f79cf597e09ad7": {
  "num_adds_if": 0,
  "num_dels_if": 0,
  "num_mod_total_if": 0,
  "num_adds_loop": 0,
  "num_dels_loop": 0,
  "num_mod_total_loop": 0,
  "file_hash": "d9ae2bad5c92cd116e3daedf16f79cf597e09ad7",
  "num_adds": 3,
  "num_dels": 25,
  "num_mod_lns_total": 28,
  "mod_files_lst": [
   "arch/powerpc/kernel/irq.c",
   "arch/powerpc/platforms/iseries/irq.c"
  ],
  "entropy": 0.49123734182433315
 }
}